edzipdataset/__init__.py
edzipdataset/dsutil.py
edzipdataset/fsspecutil.py
edzipdataset/processlocal.py
edzipdataset/sqlite.py
edzipdataset-0.1.49.dist-info/METADATA
edzipdataset-0.1.49.dist-info/WHEEL
edzipdataset-0.1.49.dist-info/RECORD
